setup.cfg
setup.py
onepassword/__init__.py
onepassword/_pbkdf2_cryptography.py
onepassword/_pbkdf2_nettle.py
onepassword/crypt_util.py
onepassword/item.py
onepassword/keychain.py
onepassword/padding.py
onepassword/pbkdf1.py
onepassword/pbkdf2.py
onepassword/util.py
onepasswordpy.egg-info/PKG-INFO
onepasswordpy.egg-info/SOURCES.txt
onepasswordpy.egg-info/dependency_links.txt
onepasswordpy.egg-info/requires.txt
onepasswordpy.egg-info/top_level.txt