Metadata-Version: 1.1
Name: onepasswordpy
Version: 0.0.3
Summary: Python tools for reading 1Password data files
Home-page: http://github.com/Roguelazer/onepasswordpy
Author: James Brown
Author-email: Roguelazer@gmail.com
License: UNKNOWN
Platform: UNKNOWN
Classifier: Programming Language :: Python
Classifier: Programming Language :: Python :: 2.6
Classifier: Programming Language :: Python :: 2.7
Classifier: Programming Language :: Python :: 3.3
Classifier: Operating System :: OS Independent
Classifier: License :: OSI Approved :: ISC License (ISCL)
Classifier: Intended Audience :: Developers
Classifier: Development Status :: 3 - Alpha
Classifier: Topic :: Security
Classifier: Topic :: Software Development :: Libraries
Provides: onepassword
